daft_scraper/__init__.py
daft_scraper/cli/__init__.py
daft_scraper/listing.py
daft_scraper/search/__init__.py
daft_scraper/search/options.py
daft_scraper/search/options_location.py
daft_scraper-1.4.0.dist-info/LICENSE
daft_scraper-1.4.0.dist-info/METADATA
daft_scraper-1.4.0.dist-info/WHEEL
daft_scraper-1.4.0.dist-info/entry_points.txt
daft_scraper-1.4.0.dist-info/RECORD
