Metadata-Version: 2.3
Name: daft-scraper
Version: 1.4.0
Summary: A webscraper for Daft.ie
License: MIT
Author: Evan Smith
Author-email: me@iamevan.me
Requires-Python: >=3.7,<4.0
Classifier: License :: OSI Approved :: MIT License
Classifier: Programming Language :: Python :: 3
Classifier: Programming Language :: Python :: 3.7
Classifier: Programming Language :: Python :: 3.8
Classifier: Programming Language :: Python :: 3.9
Classifier: Programming Language :: Python :: 3.10
Classifier: Programming Language :: Python :: 3.11
Classifier: Programming Language :: Python :: 3.12
Classifier: Programming Language :: Python :: 3.13
Requires-Dist: beautifulsoup4 (>=4.9.3,<5.0.0)
Requires-Dist: marshmallow (>=3.9.1,<4.0.0)
Requires-Dist: requests (>=2.25.0,<3.0.0)
Requires-Dist: tabulate (>=0.8.7,<0.9.0)
Requires-Dist: typer (>=0.3.2,<0.4.0)
Requires-Dist: urllib3 (>=1.26.2,<2.0.0)
